purltools/__init__.py
purltools/_git.py
purltools/main.py
purltools/meta.py
purltools/purl2cd.py
purltools/test_meta.py
purltools/url_purl.py
purl_tools-0.2.3.dist-info/METADATA
purl_tools-0.2.3.dist-info/WHEEL
purl_tools-0.2.3.dist-info/entry_points.txt
purl_tools-0.2.3.dist-info/licenses/LICENSE
purl_tools-0.2.3.dist-info/licenses/LICENSES/Apache-2.0.txt
purl_tools-0.2.3.dist-info/licenses/LICENSES/CC-BY-4.0.txt
purl_tools-0.2.3.dist-info/RECORD
