Metadata-Version: 2.4
Name: purl-tools
Version: 0.2.3
Summary: A small library that supports with various tasks around Package URLs
License: Apache-2.0
License-File: LICENSE
License-File: LICENSES/Apache-2.0.txt
License-File: LICENSES/CC-BY-4.0.txt
Keywords: compliance,clearlydefined,purl
Author: Max Mehl
Author-email: max.mehl@deutschebahn.com
Requires-Python: >=3.10,<4.0
Classifier: Development Status :: 5 - Production/Stable
Classifier: Environment :: Console
Classifier: License :: OSI Approved :: Apache Software License
Classifier: Programming Language :: Python :: 3
Classifier: Programming Language :: Python :: 3.10
Classifier: Programming Language :: Python :: 3.11
Classifier: Programming Language :: Python :: 3.12
Classifier: Programming Language :: Python :: 3.13
Classifier: Programming Language :: Python :: 3.14
Classifier: Topic :: Software Development
Requires-Dist: packageurl-python (>=0.17.5,<0.18.0)
Requires-Dist: requests (>=2.32.5,<3.0.0)
Project-URL: Repository, https://github.com/OpenRailAssociation/purl-tools
